picklepipe/__init__.py
picklepipe/jsonpipe.py
picklepipe/marshalpipe.py
picklepipe/picklepipe.py
picklepipe/pipe.py
picklepipe/socketpair.py
picklepipe/timeout.py
picklepipe-1.1.1.dist-info/DESCRIPTION.rst
picklepipe-1.1.1.dist-info/METADATA
picklepipe-1.1.1.dist-info/RECORD
picklepipe-1.1.1.dist-info/WHEEL
picklepipe-1.1.1.dist-info/metadata.json
picklepipe-1.1.1.dist-info/top_level.txt
