Metadata-Version: 2.0
Name: picklepipe
Version: 1.1.1
Summary: Python pickling and marshal protocol over any network interface.
Home-page: http://picklepipe.readthedocs.io
Author: Seth Michael Larson
Author-email: sethmichaellarson@protonmail.com
License: MIT
Keywords: picklepipe
Platform: UNKNOWN
Classifier: Intended Audience :: Developers
Classifier: License :: OSI Approved :: MIT License
Classifier: Natural Language :: English
Classifier: Operating System :: OS Independent
Classifier: Programming Language :: Python :: 2
Classifier: Programming Language :: Python :: 2.7
Classifier: Programming Language :: Python :: 3
Classifier: Programming Language :: Python :: 3.3
Classifier: Programming Language :: Python :: 3.4
Classifier: Programming Language :: Python :: 3.5
Classifier: Programming Language :: Python :: 3.6
Requires-Dist: monotonic
Requires-Dist: selectors2
